msds/__init__.py
msds/backTest/Evaluate.py
msds/backTest/Position.py
msds/backTest/__init__.py
msds/backTest/getBackTest.py
msds/base/__init__.py
msds/base/data.py
msds/base/path.py
msds/base/request.py
msds/base/util.py
msds/base/__initial__/__init__.py
msds/base/__initial__/main.ini
msds/base/__initial__/main.py
msds/base/__initial__/__btcache__/.keep
msds/candleData/getCandleData.py
msds/config/__init__.py
msds/config/config.py
msds/firmOffer/Config.py
msds/firmOffer/Function.py
msds/firmOffer/Signals.py
msds/firmOffer/cc_dma_main.py
msds/strategy/double_moving_average/main.py
msds/website/__init__.py
msds/website/flask.py
msds/website/app/__init__.py
msds/website/app/home.py
msds/website/routes/__init__.py
msds/website/view/static/main.css
msds/website/view/static/main.js
msds/website/view/templates/backtest.html
msds-0.0.37.dist-info/METADATA
msds-0.0.37.dist-info/WHEEL
msds-0.0.37.dist-info/entry_points.txt
msds-0.0.37.dist-info/top_level.txt
msds-0.0.37.dist-info/RECORD
